ribotools/__init__.py
ribotools/defaults.py
ribotools/htseq_wf/__init__.py
ribotools/htseq_wf/alignment_workflow.py
ribotools/htseq_wf/call_htseq_count.py
ribotools/htseq_wf/get_ribo_periodic.py
ribotools/htseq_wf/keep_ribo_periodic.py
ribotools/htseq_wf/run_htseq_workflow.py
ribotools/htseq_wf/rnaseq/__init__.py
ribotools/pgrms/__init__.py
ribotools/pgrms/get_all_bam_periodic.py
ribotools/pgrms/get_gtf_from_predictions.py
ribotools/scripts/__init__.py
ribotools/scripts/__main__.py
ribotools/scripts/get-sample-table
ribotools/scripts/run-dea
ribotools/scripts/run-tea
ribotools/utils/__init__.py
ribotools/utils/cl_utils.py
ribotools/utils/filenames.py
ribotools-1.0.4.dist-info/LICENSE
ribotools-1.0.4.dist-info/METADATA
ribotools-1.0.4.dist-info/WHEEL
ribotools-1.0.4.dist-info/entry_points.txt
ribotools-1.0.4.dist-info/top_level.txt
ribotools-1.0.4.dist-info/RECORD
