Metadata-Version: 2.1
Name: ribotools
Version: 1.0.4
Summary: Ribo-seq analysis tools associated with the Rp-Bp package and more
Author: Etienne Boileau
Maintainer-email: Etienne Boileau <boileau@uni-heidelberg.de>
License: MIT
Project-URL: Github, https://github.com/eboileau/ribotools/
Project-URL: Issues, https://github.com/eboileau/ribotools/issues
Keywords: bioinformatics,riboseq,open reading frame discovery,translation
Classifier: Development Status :: 2 - Pre-Alpha
Classifier: Intended Audience :: Science/Research
Classifier: Topic :: Scientific/Engineering :: Bio-Informatics
Classifier: License :: OSI Approved :: MIT License
Classifier: Operating System :: MacOS :: MacOS X
Classifier: Operating System :: POSIX :: Linux
Classifier: Programming Language :: Python :: 3 :: Only
Classifier: Programming Language :: Python :: 3.7
Classifier: Programming Language :: Python :: 3.8
Classifier: Programming Language :: Python :: 3.9
Classifier: Programming Language :: Python :: 3.10
Requires-Python: <3.11,>=3.7
License-File: LICENSE
Requires-Dist: rpbp >=3.0.1
Requires-Dist: htseq >=2.0.2
Provides-Extra: docs
Requires-Dist: ipykernel ; extra == 'docs'
Requires-Dist: matplotlib ; extra == 'docs'
Requires-Dist: nbsphinx ; extra == 'docs'
Requires-Dist: pandoc ; extra == 'docs'
Requires-Dist: sphinx >=4.5.0 ; extra == 'docs'
Requires-Dist: sphinx-rtd-theme >=1.0.0 ; extra == 'docs'
Requires-Dist: furo ; extra == 'docs'
Requires-Dist: sphinx-argparse ; extra == 'docs'
Requires-Dist: sphinx-copybutton ; extra == 'docs'
Provides-Extra: tests
Requires-Dist: pytest ; extra == 'tests'
Requires-Dist: pytest-cov ; extra == 'tests'
Requires-Dist: pytest-depends ; extra == 'tests'
